access_parser/__init__.py
access_parser/access_parser.py
access_parser/parsing_primitives.py
access_parser/utils.py
access_parser-0.0.4.dist-info/LICENSE
access_parser-0.0.4.dist-info/METADATA
access_parser-0.0.4.dist-info/WHEEL
access_parser-0.0.4.dist-info/top_level.txt
access_parser-0.0.4.dist-info/RECORD
