Metadata-Version: 2.1
Name: access-parser
Version: 0.0.4
Summary: Access database (*.mdb, *.accdb) parser
Home-page: https://github.com/ClarotyICS/access_parser
Author: Uri Katz
Author-email: uri.k@claroty.com
License: UNKNOWN
Platform: UNKNOWN
Classifier: Programming Language :: Python :: 3
Classifier: License :: OSI Approved :: Apache Software License
Classifier: Operating System :: OS Independent
Requires-Python: >=3.6
Requires-Dist: construct
Requires-Dist: tabulate
